antipasti/__init__.py
antipasti/config.py
antipasti/model/__init__.py
antipasti/model/model.py
antipasti/preprocessing/__init__.py
antipasti/preprocessing/preprocessing.py
antipasti/utils/__init__.py
antipasti/utils/biology_utils.py
antipasti/utils/explaining_utils.py
antipasti/utils/generic_utils.py
antipasti/utils/torch_utils.py
nma-cnn/__init__.py
nma-cnn/config.py
nma-cnn/model/__init__.py
nma-cnn/plots/__init__.py
nma-cnn/preprocessing/__init__.py
nma-cnn/preprocessing/preprocessing.py
nma-cnn/utils/__init__.py
nma-cnn/utils/generic_utils.py
nmacnn/__init__.py
nmacnn/config.py
nmacnn/model/__init__.py
nmacnn/model/model.py
nmacnn/plots/__init__.py
nmacnn/preprocessing/__init__.py
nmacnn/preprocessing/preprocessing.py
nmacnn/utils/__init__.py
nmacnn/utils/explaining_utils.py
nmacnn/utils/generic_utils.py
nmacnn/utils/torch_utils.py
ANTIPASTI-1.2.dist-info/AUTHORS.md
ANTIPASTI-1.2.dist-info/LICENSE
ANTIPASTI-1.2.dist-info/METADATA
ANTIPASTI-1.2.dist-info/WHEEL
ANTIPASTI-1.2.dist-info/top_level.txt
ANTIPASTI-1.2.dist-info/RECORD
