Metadata-Version: 2.1
Name: ANTIPASTI
Version: 1.2
Summary: Deep Learning model that predicts the binding affinity of antibodies from their three-dimensional structure.
Author: Kevin Michalewicz
Author-email: k.michalewicz22@imperial.ac.uk
License-File: LICENSE
License-File: AUTHORS.md
Requires-Dist: adabelief-pytorch
Requires-Dist: biopython
Requires-Dist: matplotlib
Requires-Dist: numpy
Requires-Dist: opencv-python
Requires-Dist: optuna
Requires-Dist: pandas
Requires-Dist: requests
Requires-Dist: scikit-learn
Requires-Dist: scipy
Requires-Dist: torch
Requires-Dist: torchmetrics
Requires-Dist: umap-learn
